agentscraper/__init__.py
agentscraper/config.py
agentscraper/main.py
agentscraper/utils.py
agentscraper/agent/BaseAgent.py
agentscraper/agent/QueryAgent.py
agentscraper/agent/TitleAgent.py
agentscraper/agent/__init__.py
agentscraper/llm/__init__.py
agentscraper/llm/groq.py
agentscraper/llm/provider.py
agentscraper/scrapers/__init__.py
agentscraper/tests/__init__.py
agentscraper/tests/test_agents.py
agentscraper/tests/test_scrapers.py
agentscraper-0.1.0.dist-info/METADATA
agentscraper-0.1.0.dist-info/WHEEL
agentscraper-0.1.0.dist-info/entry_points.txt
agentscraper-0.1.0.dist-info/top_level.txt
agentscraper-0.1.0.dist-info/RECORD
